userdatamodel/__init__.py
userdatamodel/driver.py
userdatamodel/init_defaults.py
userdatamodel/models.py
userdatamodel/syncing/dbgap.py
userdatamodel/user.py
userdatamodel-3.1.0.dist-info/METADATA
userdatamodel-3.1.0.dist-info/WHEEL
userdatamodel-3.1.0.dist-info/entry_points.txt
userdatamodel-3.1.0.dist-info/licenses/LICENSE
userdatamodel-3.1.0.dist-info/licenses/NOTICE
userdatamodel-3.1.0.dist-info/RECORD
