Metadata-Version: 2.4
Name: userdatamodel
Version: 3.1.0
Summary: PDC data model for user management
License: Apache-2.0
License-File: LICENSE
License-File: NOTICE
Author: CTDS UChicago
Author-email: cdis@uchicago.edu
Requires-Python: >=3.13,<4
Classifier: License :: OSI Approved :: Apache Software License
Classifier: Programming Language :: Python :: 3
Classifier: Programming Language :: Python :: 3.13
Classifier: Programming Language :: Python :: 3.14
Requires-Dist: cdislogging (>=1,<2)
Requires-Dist: sqlalchemy (>=1.3.0)
Project-URL: Repository, https://github.com/uc-cdis/userdatamodel
